[
  {
    "date": "2027-01-01",
    "ventas": 17867.29,
    "upper": 20547.39,
    "lower": 15187.2
  },
  {
    "date": "2027-01-02",
    "ventas": 17929.41,
    "upper": 20618.82,
    "lower": 15240
  },
  {
    "date": "2027-01-03",
    "ventas": 18744.79,
    "upper": 21556.51,
    "lower": 15933.07
  },
  {
    "date": "2027-01-04",
    "ventas": 18812.96,
    "upper": 21634.91,
    "lower": 15991.02
  },
  {
    "date": "2027-01-05",
    "ventas": 19765.34,
    "upper": 22730.14,
    "lower": 16800.54
  },
  {
    "date": "2027-01-06",
    "ventas": 20591.95,
    "upper": 23680.74,
    "lower": 17503.16
  },
  {
    "date": "2027-01-07",
    "ventas": 20939.3,
    "upper": 24080.2,
    "lower": 17798.41
  },
  {
    "date": "2027-01-08",
    "ventas": 21978.77,
    "upper": 25275.58,
    "lower": 18681.95
  },
  {
    "date": "2027-01-09",
    "ventas": 23133.64,
    "upper": 26603.68,
    "lower": 19663.59
  },
  {
    "date": "2027-01-10",
    "ventas": 23326.71,
    "upper": 26825.72,
    "lower": 19827.71
  },
  {
    "date": "2027-01-11",
    "ventas": 24557.51,
    "upper": 28241.14,
    "lower": 20873.88
  },
  {
    "date": "2027-01-12",
    "ventas": 25717.67,
    "upper": 29575.32,
    "lower": 21860.02
  },
  {
    "date": "2027-01-13",
    "ventas": 25727.55,
    "upper": 29586.69,
    "lower": 21868.42
  },
  {
    "date": "2027-01-14",
    "ventas": 26227.31,
    "upper": 30161.41,
    "lower": 22293.21
  },
  {
    "date": "2027-01-15",
    "ventas": 28140.68,
    "upper": 32361.78,
    "lower": 23919.58
  },
  {
    "date": "2027-01-16",
    "ventas": 28054.89,
    "upper": 32263.13,
    "lower": 23846.66
  },
  {
    "date": "2027-01-17",
    "ventas": 29527.67,
    "upper": 33956.82,
    "lower": 25098.52
  },
  {
    "date": "2027-01-18",
    "ventas": 31580.23,
    "upper": 36317.27,
    "lower": 26843.2
  },
  {
    "date": "2027-01-19",
    "ventas": 32328.51,
    "upper": 37177.79,
    "lower": 27479.24
  },
  {
    "date": "2027-01-20",
    "ventas": 32813.98,
    "upper": 37736.08,
    "lower": 27891.89
  },
  {
    "date": "2027-01-21",
    "ventas": 32798.13,
    "upper": 37717.85,
    "lower": 27878.41
  },
  {
    "date": "2027-01-22",
    "ventas": 34795.69,
    "upper": 40015.04,
    "lower": 29576.33
  },
  {
    "date": "2027-01-23",
    "ventas": 35718.73,
    "upper": 41076.54,
    "lower": 30360.92
  },
  {
    "date": "2027-01-24",
    "ventas": 36577.78,
    "upper": 42064.45,
    "lower": 31091.11
  },
  {
    "date": "2027-01-25",
    "ventas": 38943.76,
    "upper": 44785.32,
    "lower": 33102.19
  },
  {
    "date": "2027-01-26",
    "ventas": 39487.92,
    "upper": 45411.11,
    "lower": 33564.73
  },
  {
    "date": "2027-01-27",
    "ventas": 40372.86,
    "upper": 46428.79,
    "lower": 34316.93
  },
  {
    "date": "2027-01-28",
    "ventas": 42662.21,
    "upper": 49061.54,
    "lower": 36262.88
  },
  {
    "date": "2027-01-29",
    "ventas": 42555.35,
    "upper": 48938.65,
    "lower": 36172.05
  },
  {
    "date": "2027-01-30",
    "ventas": 44562.93,
    "upper": 51247.37,
    "lower": 37878.49
  },
  {
    "date": "2027-01-31",
    "ventas": 47067.85,
    "upper": 54128.02,
    "lower": 40007.67
  },
  {
    "date": "2027-02-01",
    "ventas": 46800.39,
    "upper": 53820.45,
    "lower": 39780.33
  },
  {
    "date": "2027-02-02",
    "ventas": 46853.45,
    "upper": 53881.47,
    "lower": 39825.43
  },
  {
    "date": "2027-02-03",
    "ventas": 51685.1,
    "upper": 59437.87,
    "lower": 43932.34
  },
  {
    "date": "2027-02-04",
    "ventas": 51894.14,
    "upper": 59678.26,
    "lower": 44110.02
  },
  {
    "date": "2027-02-05",
    "ventas": 55243.79,
    "upper": 63530.36,
    "lower": 46957.23
  },
  {
    "date": "2027-02-06",
    "ventas": 55253.29,
    "upper": 63541.28,
    "lower": 46965.3
  },
  {
    "date": "2027-02-07",
    "ventas": 55178.71,
    "upper": 63455.51,
    "lower": 46901.9
  },
  {
    "date": "2027-02-08",
    "ventas": 58624.97,
    "upper": 67418.72,
    "lower": 49831.22
  },
  {
    "date": "2027-02-09",
    "ventas": 61829.42,
    "upper": 71103.83,
    "lower": 52555.01
  },
  {
    "date": "2027-02-10",
    "ventas": 61956.53,
    "upper": 71250.01,
    "lower": 52663.05
  },
  {
    "date": "2027-02-11",
    "ventas": 61387.35,
    "upper": 70595.45,
    "lower": 52179.25
  },
  {
    "date": "2027-02-12",
    "ventas": 61186.98,
    "upper": 70365.03,
    "lower": 52008.93
  },
  {
    "date": "2027-02-13",
    "ventas": 65411.84,
    "upper": 75223.62,
    "lower": 55600.07
  },
  {
    "date": "2027-02-14",
    "ventas": 68250.79,
    "upper": 78488.4,
    "lower": 58013.17
  },
  {
    "date": "2027-02-15",
    "ventas": 68879.29,
    "upper": 79211.19,
    "lower": 58547.4
  },
  {
    "date": "2027-02-16",
    "ventas": 70623.44,
    "upper": 81216.96,
    "lower": 60029.93
  },
  {
    "date": "2027-02-17",
    "ventas": 72115.32,
    "upper": 82932.61,
    "lower": 61298.02
  },
  {
    "date": "2027-02-18",
    "ventas": 75671.23,
    "upper": 87021.92,
    "lower": 64320.55
  },
  {
    "date": "2027-02-19",
    "ventas": 74318.36,
    "upper": 85466.12,
    "lower": 63170.61
  },
  {
    "date": "2027-02-20",
    "ventas": 86630.44,
    "upper": 99625,
    "lower": 73635.87
  },
  {
    "date": "2027-02-21",
    "ventas": 86495.18,
    "upper": 99469.46,
    "lower": 73520.91
  },
  {
    "date": "2027-02-22",
    "ventas": 89749.89,
    "upper": 103212.38,
    "lower": 76287.41
  },
  {
    "date": "2027-02-23",
    "ventas": 88512.49,
    "upper": 101789.37,
    "lower": 75235.62
  },
  {
    "date": "2027-02-24",
    "ventas": 89077.89,
    "upper": 102439.58,
    "lower": 75716.21
  },
  {
    "date": "2027-02-25",
    "ventas": 88226.63,
    "upper": 101460.63,
    "lower": 74992.64
  },
  {
    "date": "2027-02-26",
    "ventas": 100000.21,
    "upper": 115000.24,
    "lower": 85000.18
  },
  {
    "date": "2027-02-27",
    "ventas": 99483.06,
    "upper": 114405.52,
    "lower": 84560.6
  },
  {
    "date": "2027-02-28",
    "ventas": 98866.96,
    "upper": 113697,
    "lower": 84036.92
  },
  {
    "date": "2027-03-01",
    "ventas": 103014.18,
    "upper": 118466.31,
    "lower": 87562.05
  },
  {
    "date": "2027-03-02",
    "ventas": 104831.14,
    "upper": 120555.81,
    "lower": 89106.47
  },
  {
    "date": "2027-03-03",
    "ventas": 103802.6,
    "upper": 119373,
    "lower": 88232.21
  },
  {
    "date": "2027-03-04",
    "ventas": 103547.31,
    "upper": 119079.41,
    "lower": 88015.22
  },
  {
    "date": "2027-03-05",
    "ventas": 99960.91,
    "upper": 114955.05,
    "lower": 84966.78
  },
  {
    "date": "2027-03-06",
    "ventas": 100477.46,
    "upper": 115549.08,
    "lower": 85405.84
  },
  {
    "date": "2027-03-07",
    "ventas": 99031.02,
    "upper": 113885.67,
    "lower": 84176.36
  },
  {
    "date": "2027-03-08",
    "ventas": 100457.31,
    "upper": 115525.91,
    "lower": 85388.72
  },
  {
    "date": "2027-03-09",
    "ventas": 99239.88,
    "upper": 114125.86,
    "lower": 84353.9
  },
  {
    "date": "2027-03-10",
    "ventas": 100445.13,
    "upper": 115511.9,
    "lower": 85378.36
  },
  {
    "date": "2027-03-11",
    "ventas": 98809.74,
    "upper": 113631.2,
    "lower": 83988.28
  },
  {
    "date": "2027-03-12",
    "ventas": 99960.91,
    "upper": 114955.05,
    "lower": 84966.78
  },
  {
    "date": "2027-03-13",
    "ventas": 100477.46,
    "upper": 115549.08,
    "lower": 85405.84
  },
  {
    "date": "2027-03-14",
    "ventas": 99031.02,
    "upper": 113885.67,
    "lower": 84176.36
  },
  {
    "date": "2027-03-15",
    "ventas": 100457.31,
    "upper": 115525.91,
    "lower": 85388.72
  },
  {
    "date": "2027-03-16",
    "ventas": 99239.88,
    "upper": 114125.86,
    "lower": 84353.9
  },
  {
    "date": "2027-03-17",
    "ventas": 100445.13,
    "upper": 115511.9,
    "lower": 85378.36
  },
  {
    "date": "2027-03-18",
    "ventas": 99192.75,
    "upper": 114071.66,
    "lower": 84313.84
  },
  {
    "date": "2027-03-19",
    "ventas": 99960.91,
    "upper": 114955.05,
    "lower": 84966.78
  },
  {
    "date": "2027-03-20",
    "ventas": 100477.46,
    "upper": 115549.08,
    "lower": 85405.84
  },
  {
    "date": "2027-03-21",
    "ventas": 99031.02,
    "upper": 113885.67,
    "lower": 84176.36
  },
  {
    "date": "2027-03-22",
    "ventas": 100457.31,
    "upper": 115525.91,
    "lower": 85388.72
  },
  {
    "date": "2027-03-23",
    "ventas": 99239.88,
    "upper": 114125.86,
    "lower": 84353.9
  },
  {
    "date": "2027-03-24",
    "ventas": 100445.13,
    "upper": 115511.9,
    "lower": 85378.36
  },
  {
    "date": "2027-03-25",
    "ventas": 99232.21,
    "upper": 114117.04,
    "lower": 84347.38
  },
  {
    "date": "2027-03-26",
    "ventas": 99960.91,
    "upper": 114955.05,
    "lower": 84966.78
  },
  {
    "date": "2027-03-27",
    "ventas": 100477.46,
    "upper": 115549.08,
    "lower": 85405.84
  },
  {
    "date": "2027-03-28",
    "ventas": 99031.02,
    "upper": 113885.67,
    "lower": 84176.36
  },
  {
    "date": "2027-03-29",
    "ventas": 100457.31,
    "upper": 115525.91,
    "lower": 85388.72
  },
  {
    "date": "2027-03-30",
    "ventas": 99239.88,
    "upper": 114125.86,
    "lower": 84353.9
  },
  {
    "date": "2027-03-31",
    "ventas": 100445.13,
    "upper": 115511.9,
    "lower": 85378.36
  },
  {
    "date": "2027-04-01",
    "ventas": 111992.61,
    "upper": 128791.5,
    "lower": 95193.72
  },
  {
    "date": "2027-04-02",
    "ventas": 112667.94,
    "upper": 129568.13,
    "lower": 95767.75
  },
  {
    "date": "2027-04-03",
    "ventas": 113184.49,
    "upper": 130162.16,
    "lower": 96206.81
  },
  {
    "date": "2027-04-04",
    "ventas": 113637.74,
    "upper": 130683.4,
    "lower": 96592.08
  },
  {
    "date": "2027-04-05",
    "ventas": 113249.08,
    "upper": 130236.44,
    "lower": 96261.72
  },
  {
    "date": "2027-04-06",
    "ventas": 112031.65,
    "upper": 128836.4,
    "lower": 95226.9
  },
  {
    "date": "2027-04-07",
    "ventas": 113236.9,
    "upper": 130222.44,
    "lower": 96251.37
  },
  {
    "date": "2027-04-08",
    "ventas": 117148.1,
    "upper": 134720.32,
    "lower": 99575.89
  },
  {
    "date": "2027-04-09",
    "ventas": 130853.83,
    "upper": 150481.9,
    "lower": 111225.75
  },
  {
    "date": "2027-04-10",
    "ventas": 130962.6,
    "upper": 150606.99,
    "lower": 111318.21
  },
  {
    "date": "2027-04-11",
    "ventas": 132378.3,
    "upper": 152235.04,
    "lower": 112521.55
  },
  {
    "date": "2027-04-12",
    "ventas": 128716.77,
    "upper": 148024.28,
    "lower": 109409.25
  },
  {
    "date": "2027-04-13",
    "ventas": 126652.62,
    "upper": 145650.51,
    "lower": 107654.73
  },
  {
    "date": "2027-04-14",
    "ventas": 127854.46,
    "upper": 147032.62,
    "lower": 108676.29
  },
  {
    "date": "2027-04-15",
    "ventas": 130125.14,
    "upper": 149643.91,
    "lower": 110606.37
  },
  {
    "date": "2027-04-16",
    "ventas": 178188.62,
    "upper": 204916.91,
    "lower": 151460.33
  },
  {
    "date": "2027-04-17",
    "ventas": 201858.41,
    "upper": 232137.17,
    "lower": 171579.65
  },
  {
    "date": "2027-04-18",
    "ventas": 176977.65,
    "upper": 203524.3,
    "lower": 150431
  },
  {
    "date": "2027-04-19",
    "ventas": 202077.54,
    "upper": 232389.17,
    "lower": 171765.91
  },
  {
    "date": "2027-04-20",
    "ventas": 186811.26,
    "upper": 214832.95,
    "lower": 158789.57
  },
  {
    "date": "2027-04-21",
    "ventas": 198863.96,
    "upper": 228693.56,
    "lower": 169034.37
  },
  {
    "date": "2027-04-22",
    "ventas": 207703.66,
    "upper": 238859.21,
    "lower": 176548.11
  },
  {
    "date": "2027-04-23",
    "ventas": 204390.83,
    "upper": 235049.45,
    "lower": 173732.2
  },
  {
    "date": "2027-04-24",
    "ventas": 218303.62,
    "upper": 251049.17,
    "lower": 185558.08
  },
  {
    "date": "2027-04-25",
    "ventas": 212214.35,
    "upper": 244046.5,
    "lower": 180382.2
  },
  {
    "date": "2027-04-26",
    "ventas": 225195.69,
    "upper": 258975.04,
    "lower": 191416.33
  },
  {
    "date": "2027-04-27",
    "ventas": 225200.67,
    "upper": 258980.78,
    "lower": 191420.57
  },
  {
    "date": "2027-04-28",
    "ventas": 236157.12,
    "upper": 271580.69,
    "lower": 200733.55
  },
  {
    "date": "2027-04-29",
    "ventas": 238501.51,
    "upper": 274276.73,
    "lower": 202726.28
  },
  {
    "date": "2027-04-30",
    "ventas": 242876.1,
    "upper": 279307.51,
    "lower": 206444.68
  },
  {
    "date": "2027-05-01",
    "ventas": 243457.97,
    "upper": 279976.66,
    "lower": 206939.27
  },
  {
    "date": "2027-05-02",
    "ventas": 238169.31,
    "upper": 273894.71,
    "lower": 202443.92
  },
  {
    "date": "2027-05-03",
    "ventas": 217436.03,
    "upper": 250051.43,
    "lower": 184820.62
  },
  {
    "date": "2027-05-04",
    "ventas": 222143.83,
    "upper": 255465.41,
    "lower": 188822.26
  },
  {
    "date": "2027-05-05",
    "ventas": 226616.3,
    "upper": 260608.75,
    "lower": 192623.86
  },
  {
    "date": "2027-05-06",
    "ventas": 232940.46,
    "upper": 267881.53,
    "lower": 197999.39
  },
  {
    "date": "2027-05-07",
    "ventas": 237159.63,
    "upper": 272733.57,
    "lower": 201585.69
  },
  {
    "date": "2027-05-08",
    "ventas": 236217.19,
    "upper": 271649.77,
    "lower": 200784.61
  },
  {
    "date": "2027-05-09",
    "ventas": 229912.61,
    "upper": 264399.5,
    "lower": 195425.72
  },
  {
    "date": "2027-05-10",
    "ventas": 227243.06,
    "upper": 261329.52,
    "lower": 193156.6
  },
  {
    "date": "2027-05-11",
    "ventas": 226368.47,
    "upper": 260323.74,
    "lower": 192413.2
  },
  {
    "date": "2027-05-12",
    "ventas": 226228.06,
    "upper": 260162.27,
    "lower": 192293.85
  },
  {
    "date": "2027-05-13",
    "ventas": 232940.46,
    "upper": 267881.53,
    "lower": 197999.39
  },
  {
    "date": "2027-05-14",
    "ventas": 237159.63,
    "upper": 272733.57,
    "lower": 201585.69
  },
  {
    "date": "2027-05-15",
    "ventas": 236217.19,
    "upper": 271649.77,
    "lower": 200784.61
  },
  {
    "date": "2027-05-16",
    "ventas": 229912.61,
    "upper": 264399.5,
    "lower": 195425.72
  },
  {
    "date": "2027-05-17",
    "ventas": 217436.03,
    "upper": 250051.43,
    "lower": 184820.62
  },
  {
    "date": "2027-05-18",
    "ventas": 222143.83,
    "upper": 255465.41,
    "lower": 188822.26
  },
  {
    "date": "2027-05-19",
    "ventas": 226616.3,
    "upper": 260608.75,
    "lower": 192623.86
  },
  {
    "date": "2027-05-20",
    "ventas": 232940.46,
    "upper": 267881.53,
    "lower": 197999.39
  },
  {
    "date": "2027-05-21",
    "ventas": 237159.63,
    "upper": 272733.57,
    "lower": 201585.69
  },
  {
    "date": "2027-05-22",
    "ventas": 236217.19,
    "upper": 271649.77,
    "lower": 200784.61
  },
  {
    "date": "2027-05-23",
    "ventas": 229912.61,
    "upper": 264399.5,
    "lower": 195425.72
  },
  {
    "date": "2027-05-24",
    "ventas": 227243.06,
    "upper": 261329.52,
    "lower": 193156.6
  },
  {
    "date": "2027-05-25",
    "ventas": 226368.47,
    "upper": 260323.74,
    "lower": 192413.2
  },
  {
    "date": "2027-05-26",
    "ventas": 226228.06,
    "upper": 260162.27,
    "lower": 192293.85
  },
  {
    "date": "2027-05-27",
    "ventas": 232940.46,
    "upper": 267881.53,
    "lower": 197999.39
  },
  {
    "date": "2027-05-28",
    "ventas": 237159.63,
    "upper": 272733.57,
    "lower": 201585.69
  },
  {
    "date": "2027-05-29",
    "ventas": 236217.19,
    "upper": 271649.77,
    "lower": 200784.61
  },
  {
    "date": "2027-05-30",
    "ventas": 229912.61,
    "upper": 264399.5,
    "lower": 195425.72
  },
  {
    "date": "2027-05-31",
    "ventas": 217436.03,
    "upper": 250051.43,
    "lower": 184820.62
  },
  {
    "date": "2027-06-01",
    "ventas": 222143.83,
    "upper": 255465.41,
    "lower": 188822.26
  },
  {
    "date": "2027-06-02",
    "ventas": 226616.3,
    "upper": 260608.75,
    "lower": 192623.86
  },
  {
    "date": "2027-06-03",
    "ventas": 232670.78,
    "upper": 267571.39,
    "lower": 197770.16
  },
  {
    "date": "2027-06-04",
    "ventas": 236889.94,
    "upper": 272423.43,
    "lower": 201356.45
  },
  {
    "date": "2027-06-05",
    "ventas": 235947.5,
    "upper": 271339.63,
    "lower": 200555.38
  },
  {
    "date": "2027-06-06",
    "ventas": 229642.92,
    "upper": 264089.36,
    "lower": 195196.48
  },
  {
    "date": "2027-06-07",
    "ventas": 227243.06,
    "upper": 261329.52,
    "lower": 193156.6
  },
  {
    "date": "2027-06-08",
    "ventas": 226368.47,
    "upper": 260323.74,
    "lower": 192413.2
  },
  {
    "date": "2027-06-09",
    "ventas": 226228.06,
    "upper": 260162.27,
    "lower": 192293.85
  },
  {
    "date": "2027-06-10",
    "ventas": 232670.78,
    "upper": 267571.39,
    "lower": 197770.16
  },
  {
    "date": "2027-06-11",
    "ventas": 236889.94,
    "upper": 272423.43,
    "lower": 201356.45
  },
  {
    "date": "2027-06-12",
    "ventas": 235947.5,
    "upper": 271339.63,
    "lower": 200555.38
  },
  {
    "date": "2027-06-13",
    "ventas": 229642.92,
    "upper": 264089.36,
    "lower": 195196.48
  },
  {
    "date": "2027-06-14",
    "ventas": 217436.03,
    "upper": 250051.43,
    "lower": 184820.62
  },
  {
    "date": "2027-06-15",
    "ventas": 222143.83,
    "upper": 255465.41,
    "lower": 188822.26
  },
  {
    "date": "2027-06-16",
    "ventas": 226616.3,
    "upper": 260608.75,
    "lower": 192623.86
  },
  {
    "date": "2027-06-17",
    "ventas": 232670.78,
    "upper": 267571.39,
    "lower": 197770.16
  },
  {
    "date": "2027-06-18",
    "ventas": 236889.94,
    "upper": 272423.43,
    "lower": 201356.45
  },
  {
    "date": "2027-06-19",
    "ventas": 235947.5,
    "upper": 271339.63,
    "lower": 200555.38
  },
  {
    "date": "2027-06-20",
    "ventas": 229642.92,
    "upper": 264089.36,
    "lower": 195196.48
  },
  {
    "date": "2027-06-21",
    "ventas": 227243.06,
    "upper": 261329.52,
    "lower": 193156.6
  },
  {
    "date": "2027-06-22",
    "ventas": 226368.47,
    "upper": 260323.74,
    "lower": 192413.2
  },
  {
    "date": "2027-06-23",
    "ventas": 226228.06,
    "upper": 260162.27,
    "lower": 192293.85
  },
  {
    "date": "2027-06-24",
    "ventas": 232670.78,
    "upper": 267571.39,
    "lower": 197770.16
  },
  {
    "date": "2027-06-25",
    "ventas": 236889.94,
    "upper": 272423.43,
    "lower": 201356.45
  },
  {
    "date": "2027-06-26",
    "ventas": 235947.5,
    "upper": 271339.63,
    "lower": 200555.38
  },
  {
    "date": "2027-06-27",
    "ventas": 229642.92,
    "upper": 264089.36,
    "lower": 195196.48
  },
  {
    "date": "2027-06-28",
    "ventas": 217436.03,
    "upper": 250051.43,
    "lower": 184820.62
  },
  {
    "date": "2027-06-29",
    "ventas": 222143.83,
    "upper": 255465.41,
    "lower": 188822.26
  }
]